{
    "name": "Heitor Victor Silva das Chagas Gomes",
    "age": "29 anos",

    "especialty": "Analista de Software",
    "professional_resume": "Analista de sistemas com um pouco mais de 03 anos de experiência. Experiente em varias as etapas do ciclo de desenvolvimento de projetos desktop possuindo um conhecimento profundo em desenvolvimento de sistemas, incluindo as linguagens de programação Java, C#, assim como um amplo conhecimento em SQL Server. Sólida experiência em gestão de projetos.",
        
    "city": "Araguaína",
    "uf": "TO",
    "country": "Brasil",

    "phone": "(63)99276-6139",
    "site": "heitorgomes.atwebpages.com"

}